citibox/profiling/__init__.py
citibox/profiling/config.py
citibox/profiling/profiler_service.py
citibox/profiling/profiling.py
citibox/profiling/contrib/__init__.py
citibox/profiling/contrib/profiler_service_google.py
citibox/profiling/contrib/django/__init__.py
citibox/profiling/contrib/django/profiling_middleware.py
citibox/profiling/contrib/falcon/__init__.py
citibox/profiling/contrib/falcon/memory_middleware.py
citibox/profiling/contrib/falcon/tests/__init__.py
citibox/profiling/contrib/falcon/tests/test_memory_middleware.py
citibox/profiling/contrib/tests/__init__.py
citibox/profiling/contrib/tests/test_profiler_service_google.py
citibox/profiling/tests/__init__.py
citibox/profiling/tests/test_profiler_service.py
citibox/profiling/tests/test_profiling.py
citibox_profiling-0.5.0.dist-info/METADATA
citibox_profiling-0.5.0.dist-info/WHEEL
citibox_profiling-0.5.0.dist-info/top_level.txt
citibox_profiling-0.5.0.dist-info/RECORD
