Metadata-Version: 2.1
Name: citibox-profiling
Version: 0.5.0
Summary: Citibox profiling tool
Home-page: https://github.com/citibox/citibox-profiling
Author: Citibox
License: UNKNOWN
Platform: UNKNOWN
Classifier: Programming Language :: Python :: 3
Classifier: License :: OSI Approved :: MIT License
Classifier: Operating System :: OS Independent
Requires-Python: >=3.7
Requires-Dist: protobuf ~=3.20.0
Requires-Dist: google-cloud-profiler ==2.0.4
